logurujson/__init__.py
logurujson-0.1.0.dist-info/WHEEL
logurujson-0.1.0.dist-info/METADATA
logurujson-0.1.0.dist-info/RECORD
